darker/__init__.py
darker/__main__.py
darker/chooser.py
darker/command_line.py
darker/concurrency.py
darker/config.py
darker/diff.py
darker/exceptions.py
darker/files.py
darker/fstring.py
darker/git.py
darker/help.py
darker/import_sorting.py
darker/multiline_strings.py
darker/py.typed
darker/terminal.py
darker/utils.py
darker/verification.py
darker/version.py
darker/configuration/__init__.py
darker/configuration/target_version.py
darker/formatters/__init__.py
darker/formatters/base_formatter.py
darker/formatters/black_formatter.py
darker/formatters/black_wrapper.py
darker/formatters/formatter_config.py
darker/formatters/none_formatter.py
darker/formatters/pyupgrade_config.py
darker/formatters/pyupgrade_formatter.py
darker/formatters/pyupgrade_wrapper.py
darker/formatters/ruff_formatter.py
darker/tests/__init__.py
darker/tests/conftest.py
darker/tests/examples.py
darker/tests/git_diff_example_output.py
darker/tests/helpers.py
darker/tests/test_chooser.py
darker/tests/test_command_line.py
darker/tests/test_command_line_ruff.py
darker/tests/test_concurrency.py
darker/tests/test_config.py
darker/tests/test_diff.py
darker/tests/test_difflib.py
darker/tests/test_files.py
darker/tests/test_formatters_black.py
darker/tests/test_formatters_black_compatible.py
darker/tests/test_formatters_ruff.py
darker/tests/test_fstring.py
darker/tests/test_git.py
darker/tests/test_import_sorting.py
darker/tests/test_main.py
darker/tests/test_main_drop_changes_on_unedited_lines.py
darker/tests/test_main_format_edited_parts.py
darker/tests/test_main_isort.py
darker/tests/test_main_reformat_and_flynt_single_file.py
darker/tests/test_main_revision.py
darker/tests/test_main_stdin_filename.py
darker/tests/test_multiline_strings.py
darker/tests/test_utils.py
darker/tests/test_verification.py
darker-3.0.0.dist-info/licenses/LICENSE.rst
darker-3.0.0.dist-info/METADATA
darker-3.0.0.dist-info/WHEEL
darker-3.0.0.dist-info/entry_points.txt
darker-3.0.0.dist-info/top_level.txt
darker-3.0.0.dist-info/RECORD
