Metadata-Version: 2.4
Name: darker
Version: 3.0.0
Summary: Apply Black formatting only in regions changed since last commit
Author-email: Antti Kaihola <13725+akaihola@users.noreply.github.com>
License: BSD
Project-URL: Homepage, https://github.com/akaihola/darker
Project-URL: Source Code, https://github.com/akaihola/darker
Project-URL: Change Log, https://github.com/akaihola/darker/blob/master/CHANGES.rst
Project-URL: News, https://github.com/akaihola/darker/discussions/categories/announcements
Classifier: Programming Language :: Python :: 3 :: Only
Classifier: Programming Language :: Python :: 3.9
Classifier: Programming Language :: Python :: 3.10
Classifier: Programming Language :: Python :: 3.11
Classifier: Programming Language :: Python :: 3.12
Requires-Python: >=3.9
License-File: LICENSE.rst
Requires-Dist: darkgraylib<3.0.dev0,>=2.4.0
Requires-Dist: toml>=0.10.0
Requires-Dist: typing_extensions>=4.0.1
Provides-Extra: color
Requires-Dist: Pygments>=2.15.0; extra == "color"
Provides-Extra: black
Requires-Dist: black>=24.10.0; extra == "black"
Provides-Extra: pyupgrade
Requires-Dist: pyupgrade>=2.31.0; extra == "pyupgrade"
Provides-Extra: flynt
Requires-Dist: flynt>=0.76; extra == "flynt"
Provides-Extra: isort
Requires-Dist: isort>=5.2.0; extra == "isort"
Provides-Extra: ruff
Requires-Dist: ruff>=0.0.292; extra == "ruff"
Provides-Extra: release
Requires-Dist: darkgray-dev-tools~=0.3.0; extra == "release"
Dynamic: description
Dynamic: description-content-type
Dynamic: license-file
